Design.v
`timescale 1ns / 1ps
//////////////////////////////////////////////////////////////////////////////////
// Company: 
// Engineer: 
// 
// Create Date: 22.04.2026 10:27:54
// Design Name: 
// Module Name: sCounter
// Project Name: 
// Target Devices: 
// Tool Versions: 
// Description: 
// 
// Dependencies: 
// 
// Revision:
// Revision 0.01 - File Created
// Additional Comments:
// 
//////////////////////////////////////////////////////////////////////////////////


module sCounter(
   input clk_i, 
   input rst_i, 
   input mode_i, 
   output [3:0]dout_o
);

//net(s)
wire Ta;
wire Tb;
wire Tc;
wire Td;
wire  Qa;
wire  Qb;
wire  Qc;
wire  Qd;
wire QaBar;
wire QbBar;
wire QcBar;
wire QdBar;

//intermediate connections
assign Ta = (mode_i & QbBar & QcBar & QdBar) | ((~mode_i) & Qb & Qc & Qd);
assign Tb = (mode_i & QcBar & QdBar) | ((~mode_i) & Qc & Qd);
assign Tc = (mode_i & QdBar) | ((~mode_i) & Qd);
assign Td = 1'b1;
assign dout_o = {Qa, Qb, Qc, Qd};

//T Flip Flop cconnections
Tff T1(.T_i(Ta), 
   .clk_i(clk_i), 
   .rst_i(rst_i), 
   .Q_o(Qa), 
   .Qbar_o(QaBar));
Tff T2(.T_i(Tb), 
   .clk_i(clk_i), 
   .rst_i(rst_i), 
   .Q_o(Qb), 
   .Qbar_o(QbBar));
Tff T3(.T_i(Tc), 
   .clk_i(clk_i), 
   .rst_i(rst_i), 
   .Q_o(Qc), 
   .Qbar_o(QcBar));
Tff T4(.T_i(Td), 
   .clk_i(clk_i), 
   .rst_i(rst_i), 
   .Q_o(Qd), 
   .Qbar_o(QdBar));

endmodule

//T Flip Flop
module Tff(
   input T_i, 
   input clk_i, 
   input rst_i, 
   output reg Q_o, 
   output Qbar_o
);

assign Qbar_o = ~Q_o;

always@(posedge clk_i)
   if(rst_i)
      Q_o <= 1'b0;
   else if(T_i)
      Q_o <= ~Q_o;

endmodule

Testbench.v
`timescale 1ns / 1ps
//////////////////////////////////////////////////////////////////////////////////
// Company: 
// Engineer: 
// 
// Create Date: 22.04.2026 10:28:25
// Design Name: 
// Module Name: tb_sCounter
// Project Name: 
// Target Devices: 
// Tool Versions: 
// Description: 
// 
// Dependencies: 
// 
// Revision:
// Revision 0.01 - File Created
// Additional Comments:
// 
//////////////////////////////////////////////////////////////////////////////////


module tb_sCounter();
reg clk_ti;
reg rst_ti; 
reg mode_ti; 
wire [3:0]dout_to;

//net(s)
reg [3:0]exp_dout;
integer count;
integer pass;
integer fail;

//instantiation 
sCounter DUT(.clk_i(clk_ti), 
   .rst_i(rst_ti), 
   .mode_i(mode_ti), 
   .dout_o(dout_to));

//initialization
initial begin
   exp_dout = 4'b0000;
   count = 0;
   pass = 0;
   fail = 0;
end

//clock
initial begin
   clk_ti = 1'b0;
   forever begin
      #5 clk_ti = ~clk_ti;
   end
end

//reset
initial begin
rst_ti = 1'b1;
#7 rst_ti = 1'b0;
end

//feeding
initial begin 
mode_ti = 1'b0;
#180 mode_ti = 1'b1;
#180 mode_ti = 1'b0;
#50 mode_ti = 1'b1;
#25 mode_ti = 1'b0;
$display("-----------");
$display("Total checks: %d | Pass: %d, Fail: %d", count, pass, fail);
$display("-----------");
#5 $finish;
end

//self check
task checker(); begin
   if(mode_ti == 1'b0) //UP
       exp_dout = exp_dout + 1;
   else  //DOWN
      exp_dout = exp_dout - 1;
   if(exp_dout !== dout_to) begin
      $display("Error | Time: %0t | Clock: %b, Reset: %b, Mode: %b | Output: %d | Expected Output: %d", $time, clk_ti, rst_ti, mode_ti, dout_to, exp_dout);
      fail = fail + 1;
   end
   else begin
      pass = pass + 1;
   end
   count = count + 1;
end
endtask

//running self check
always@(posedge clk_ti)
   if(rst_ti)
      exp_dout = 4'b0000;
   else 
      #1 checker;

//capture
initial begin
   $dumpvars(0, tb_sCounter);
   $dumpfile("sCounter.vcd");
end

endmodule

dump.vcd
$date
   Thu Apr 23 19:54:14 2026
$end

$version
  2025.2
$end

$timescale
  1ps
$end

$scope module tb_sCounter $end
$var reg 1 ! clk_ti $end
$var reg 1 " rst_ti $end
$var reg 1 # mode_ti $end
$var wire 4 $ dout_to [3:0] $end
$var reg 4 % exp_dout [3:0] $end
$var integer 32 & count [31:0] $end
$var integer 32 ' pass [31:0] $end
$var integer 32 ( fail [31:0] $end
$scope module DUT $end
$var wire 1 ) clk_i $end
$var wire 1 * rst_i $end
$var wire 1 + mode_i $end
$var wire 4 $ dout_o [3:0] $end
$var wire 1 , Ta $end
$var wire 1 - Tb $end
$var wire 1 . Tc $end
$var wire 1 / Td $end
$var wire 1 0 Qa $end
$var wire 1 1 Qb $end
$var wire 1 2 Qc $end
$var wire 1 3 Qd $end
$var wire 1 4 QaBar $end
$var wire 1 5 QbBar $end
$var wire 1 6 QcBar $end
$var wire 1 7 QdBar $end
$scope module T1 $end
$var wire 1 , T_i $end
$var wire 1 ) clk_i $end
$var wire 1 * rst_i $end
$var reg 1 8 Q_o $end
$var wire 1 4 Qbar_o $end
$upscope $end
$scope module T2 $end
$var wire 1 - T_i $end
$var wire 1 ) clk_i $end
$var wire 1 * rst_i $end
$var reg 1 9 Q_o $end
$var wire 1 5 Qbar_o $end
$upscope $end
$scope module T3 $end
$var wire 1 . T_i $end
$var wire 1 ) clk_i $end
$var wire 1 * rst_i $end
$var reg 1 : Q_o $end
$var wire 1 6 Qbar_o $end
$upscope $end
$scope module T4 $end
$var wire 1 / T_i $end
$var wire 1 ) clk_i $end
$var wire 1 * rst_i $end
$var reg 1 ; Q_o $end
$var wire 1 7 Qbar_o $end
$upscope $end
$upscope $end
$scope task checker $end
$upscope $end
$upscope $end
$enddefinitions $end

#0
$dumpvars
0!
1"
0#
bx $
b0 %
b0 &
b0 '
b0 (
0)
1*
0+
x,
x-
x.
1/
x0
x1
x2
x3
x4
x5
x6
x7
x8
x9
x:
x;
$end

#5000
1!
b0 $
1)
0,
0-
0.
00
01
02
03
14
15
16
17
08
09
0:
0;

#7000
0"
0*

#10000
0!
0)

#15000
1!
b1 $
1)
1.
13
07
1;

#16000
b1 %
b1 &
b1 '

#20000
0!
0)

#25000
1!
b10 $
1)
0.
12
03
06
17
1:
0;

#26000
b10 %
b10 &
b10 '

#30000
0!
0)

#35000
1!
b11 $
1)
1-
1.
13
07
1;

#36000
b11 %
b11 &
b11 '

#40000
0!
0)

#45000
1!
b100 $
1)
0-
0.
11
02
03
05
16
17
19
0:
0;

#46000
b100 %
b100 &
b100 '

#50000
0!
0)

#55000
1!
b101 $
1)
1.
13
07
1;

#56000
b101 %
b101 &
b101 '

#60000
0!
0)

#65000
1!
b110 $
1)
0.
12
03
06
17
1:
0;

#66000
b110 %
b110 &
b110 '

#70000
0!
0)

#75000
1!
b111 $
1)
1,
1-
1.
13
07
1;

#76000
b111 %
b111 &
b111 '

#80000
0!
0)

#85000
1!
b1000 $
1)
0,
0-
0.
10
01
02
03
04
15
16
17
18
09
0:
0;

#86000
b1000 %
b1000 &
b1000 '

#90000
0!
0)

#95000
1!
b1001 $
1)
1.
13
07
1;

#96000
b1001 %
b1001 &
b1001 '

#100000
0!
0)

#105000
1!
b1010 $
1)
0.
12
03
06
17
1:
0;

#106000
b1010 %
b1010 &
b1010 '

#110000
0!
0)

#115000
1!
b1011 $
1)
1-
1.
13
07
1;

#116000
b1011 %
b1011 &
b1011 '

#120000
0!
0)

#125000
1!
b1100 $
1)
0-
0.
11
02
03
05
16
17
19
0:
0;

#126000
b1100 %
b1100 &
b1100 '

#130000
0!
0)

#135000
1!
b1101 $
1)
1.
13
07
1;

#136000
b1101 %
b1101 &
b1101 '

#140000
0!
0)

#145000
1!
b1110 $
1)
0.
12
03
06
17
1:
0;

#146000
b1110 %
b1110 &
b1110 '

#150000
0!
0)

#155000
1!
b1111 $
1)
1,
1-
1.
13
07
1;

#156000
b1111 %
b1111 &
b1111 '

#160000
0!
0)

#165000
1!
b0 $
1)
0,
0-
0.
00
01
02
03
14
15
16
17
08
09
0:
0;

#166000
b0 %
b10000 &
b10000 '

#170000
0!
0)

#175000
1!
b1 $
1)
1.
13
07
1;

#176000
b1 %
b10001 &
b10001 '

#180000
0!
1#
0)
1+
0.

#185000
1!
b0 $
1)
1,
1-
1.
03
17
0;

#186000
b0 %
b10010 &
b10010 '

#190000
0!
0)

#195000
1!
b1111 $
1)
0,
0-
0.
10
11
12
13
04
05
06
07
18
19
1:
1;

#196000
b1111 %
b10011 &
b10011 '

#200000
0!
0)

#205000
1!
b1110 $
1)
1.
03
17
0;

#206000
b1110 %
b10100 &
b10100 '

#210000
0!
0)

#215000
1!
b1101 $
1)
0.
02
13
16
07
0:
1;

#216000
b1101 %
b10101 &
b10101 '

#220000
0!
0)

#225000
1!
b1100 $
1)
1-
1.
03
17
0;

#226000
b1100 %
b10110 &
b10110 '

#230000
0!
0)

#235000
1!
b1011 $
1)
0-
0.
01
12
13
15
06
07
09
1:
1;

#236000
b1011 %
b10111 &
b10111 '

#240000
0!
0)

#245000
1!
b1010 $
1)
1.
03
17
0;

#246000
b1010 %
b11000 &
b11000 '

#250000
0!
0)

#255000
1!
b1001 $
1)
0.
02
13
16
07
0:
1;

#256000
b1001 %
b11001 &
b11001 '

#260000
0!
0)

#265000
1!
b1000 $
1)
1,
1-
1.
03
17
0;

#266000
b1000 %
b11010 &
b11010 '

#270000
0!
0)

#275000
1!
b111 $
1)
0,
0-
0.
00
11
12
13
14
05
06
07
08
19
1:
1;

#276000
b111 %
b11011 &
b11011 '

#280000
0!
0)

#285000
1!
b110 $
1)
1.
03
17
0;

#286000
b110 %
b11100 &
b11100 '

#290000
0!
0)

#295000
1!
b101 $
1)
0.
02
13
16
07
0:
1;

#296000
b101 %
b11101 &
b11101 '

#300000
0!
0)

#305000
1!
b100 $
1)
1-
1.
03
17
0;

#306000
b100 %
b11110 &
b11110 '

#310000
0!
0)

#315000
1!
b11 $
1)
0-
0.
01
12
13
15
06
07
09
1:
1;

#316000
b11 %
b11111 &
b11111 '

#320000
0!
0)

#325000
1!
b10 $
1)
1.
03
17
0;

#326000
b10 %
b100000 &
b100000 '

#330000
0!
0)

#335000
1!
b1 $
1)
0.
02
13
16
07
0:
1;

#336000
b1 %
b100001 &
b100001 '

#340000
0!
0)

#345000
1!
b0 $
1)
1,
1-
1.
03
17
0;

#346000
b0 %
b100010 &
b100010 '

#350000
0!
0)

#355000
1!
b1111 $
1)
0,
0-
0.
10
11
12
13
04
05
06
07
18
19
1:
1;

#356000
b1111 %
b100011 &
b100011 '

#360000
0!
0#
0)
0+
1,
1-
1.

#365000
1!
b0 $
1)
0,
0-
0.
00
01
02
03
14
15
16
17
08
09
0:
0;

#366000
b0 %
b100100 &
b100100 '

#370000
0!
0)

#375000
1!
b1 $
1)
1.
13
07
1;

#376000
b1 %
b100101 &
b100101 '

#380000
0!
0)

#385000
1!
b10 $
1)
0.
12
03
06
17
1:
0;

#386000
b10 %
b100110 &
b100110 '

#390000
0!
0)

#395000
1!
b11 $
1)
1-
1.
13
07
1;

#396000
b11 %
b100111 &
b100111 '

#400000
0!
0)

#405000
1!
b100 $
1)
0-
0.
11
02
03
05
16
17
19
0:
0;

#406000
b100 %
b101000 &
b101000 '

#410000
0!
1#
0)
1+
1-
1.

#415000
1!
b11 $
1)
0-
0.
01
12
13
15
06
07
09
1:
1;

#416000
b11 %
b101001 &
b101001 '

#420000
0!
0)

#425000
1!
b10 $
1)
1.
03
17
0;

#426000
b10 %
b101010 &
b101010 '

#430000
0!
0)

#435000
1!
0#
b11 $
1)
0+
1-
1.
13
07
1;

#436000
b11 %
b101011 &
b101011 '
